<?xml version="1.0" encoding="UTF-8"?>

<passwords>
    <password>123456</password>
    <password>123456789</password>
    <password>12345678</password>
    <password>password</password>
    <password>qwerty123</password>
    <password>qwerty1</password>
    <password>111111</password>
    <password>12345</password>
    <password>secret</password>
    <password>123123</password>
    <password>1234567890</password>
    <password>1234567</password>
    <password>000000</password>
    <password>qwerty</password>
    <password>abc123</password>
    <password>password1</password>
    <password>iloveyou</password>
    <password>11111111</password>
    <password>dragon</password>
    <password>monkey</password>
</passwords>
